README.md
setup.py
errorcalcsbeta/dialog.py
errorcalcsbeta/ecfuncs.py
errorcalcsbeta/main_window.py
errorcalcsbeta/menu_bar.py
errorcalcsbeta.egg-info/PKG-INFO
errorcalcsbeta.egg-info/SOURCES.txt
errorcalcsbeta.egg-info/dependency_links.txt
errorcalcsbeta.egg-info/requires.txt
errorcalcsbeta.egg-info/top_level.txt