Metadata-Version: 2.1
Name: errorcalcsbeta
Version: 0.4.6
Summary: GUI for error calulations
Home-page: https://github.com/leonfrcom/errorcalcs-beta
Author: lefrcom
Author-email: lefrcom@gmx.de
License: UNKNOWN
Platform: UNKNOWN
Classifier: Programming Language :: Python :: 3
Classifier: License :: OSI Approved :: MIT License
Classifier: Operating System :: OS Independent
